odoo/addons/account_banking_ach_credit_transfer/README.rst
odoo/addons/account_banking_ach_credit_transfer/__init__.py
odoo/addons/account_banking_ach_credit_transfer/__manifest__.py
odoo/addons/account_banking_ach_credit_transfer/data/account_payment_method.xml
odoo/addons/account_banking_ach_credit_transfer/demo/ach_credit_transfer_demo.xml
odoo/addons/account_banking_ach_credit_transfer/i18n/account_banking_ach_credit_transfer.pot
odoo/addons/account_banking_ach_credit_transfer/models/__init__.py
odoo/addons/account_banking_ach_credit_transfer/models/account_payment_order.py
odoo/addons/account_banking_ach_credit_transfer/readme/CONFIGURE.md
odoo/addons/account_banking_ach_credit_transfer/readme/CONTRIBUTORS.md
odoo/addons/account_banking_ach_credit_transfer/readme/DESCRIPTION.md
odoo/addons/account_banking_ach_credit_transfer/readme/INSTALL.md
odoo/addons/account_banking_ach_credit_transfer/static/description/icon.png
odoo/addons/account_banking_ach_credit_transfer/static/description/index.html
odoo/addons/account_banking_ach_credit_transfer/tests/__init__.py
odoo/addons/account_banking_ach_credit_transfer/tests/test_account_banking_ach_credit_transfer.py
odoo_addon_account_banking_ach_credit_transfer-18.0.1.0.0.3.dist-info/METADATA
odoo_addon_account_banking_ach_credit_transfer-18.0.1.0.0.3.dist-info/WHEEL
odoo_addon_account_banking_ach_credit_transfer-18.0.1.0.0.3.dist-info/top_level.txt
odoo_addon_account_banking_ach_credit_transfer-18.0.1.0.0.3.dist-info/RECORD
