Metadata-Version: 2.1
Name: odoo-addon-account_banking_ach_credit_transfer
Version: 18.0.1.0.0.3
Requires-Python: >=3.10
Requires-Dist: odoo-addon-account_banking_ach_base==18.0.*
Requires-Dist: odoo==18.0.*
Summary: Create ACH files for Credit Transfers
Home-page: https://github.com/OCA/l10n-usa
License: AGPL-3
Author: Thinkwell Designs, Odoo Community Association (OCA)
Author-email: support@odoo-community.org
Classifier: Programming Language :: Python
Classifier: Framework :: Odoo
Classifier: Framework :: Odoo :: 18.0
Classifier: License :: OSI Approved :: GNU Affero General Public License v3
